con.py
con_trefacon-0.0.1.dist-info/LICENSE
con_trefacon-0.0.1.dist-info/METADATA
con_trefacon-0.0.1.dist-info/WHEEL
con_trefacon-0.0.1.dist-info/entry_points.txt
con_trefacon-0.0.1.dist-info/top_level.txt
con_trefacon-0.0.1.dist-info/RECORD
