Metadata-Version: 2.1
Name: con-trefacon
Version: 0.0.1
Summary: Con, comme git, mais en français
Home-page: http://github.com/elbabass/con
Author: Bastien Gallay
Author-email: bastien@gallay.org
License: 3-clause BSD
Platform: UNKNOWN
Classifier: Environment :: Console
Classifier: License :: OSI Approved :: BSD License
Classifier: Operating System :: Unix
Classifier: Programming Language :: Python :: 2
Classifier: Programming Language :: Python :: 3
Classifier: Topic :: Software Development :: Build Tools
License-File: LICENSE
